otozu/config.py
otozu/converter.py
otozu/utils.py
otozu-0.1.0.dist-info/METADATA
otozu-0.1.0.dist-info/WHEEL
otozu-0.1.0.dist-info/entry_points.txt
otozu-0.1.0.dist-info/licenses/LICENSE
otozu-0.1.0.dist-info/RECORD
