Metadata-Version: 2.3
Name: otozu
Version: 0.1.0
Summary: A library for converting between audio files and spectrograms
Project-URL: Homepage, https://github.com/jyaaan/otozu
Project-URL: Bug Tracker, https://github.com/jyaaan/otozu/issues
Author-email: John Yamashiro <john.yamashiro@gmail.com>
Keywords: audio,audio analysis,audio classification,deep learning,machine learning,mel-spectrogram,model visualization,neural networks,sound processing,spectrogram
Classifier: Development Status :: 4 - Beta
Classifier: Intended Audience :: Developers
Classifier: Intended Audience :: Science/Research
Classifier: License :: OSI Approved :: MIT License
Classifier: Programming Language :: Python :: 3
Classifier: Programming Language :: Python :: 3.8
Classifier: Programming Language :: Python :: 3.9
Classifier: Programming Language :: Python :: 3.10
Classifier: Programming Language :: Python :: 3.11
Classifier: Topic :: Multimedia :: Sound/Audio :: Analysis
Classifier: Topic :: Scientific/Engineering :: Artificial Intelligence
Classifier: Topic :: Scientific/Engineering :: Image Processing
Classifier: Topic :: Scientific/Engineering :: Information Analysis
Requires-Python: >=3.8
Requires-Dist: librosa>=0.10.0
Requires-Dist: numpy>=1.20.0
Requires-Dist: pillow>=9.0.0
Requires-Dist: soundfile>=0.12.0
Requires-Dist: typer>=0.9.0
